panel_auth0_oidc/__init__.py
panel_auth0_oidc/panel_auth0_oidc.py
panel_auth0_oidc-0.1.3.dist-info/entry_points.txt
panel_auth0_oidc-0.1.3.dist-info/LICENSE
panel_auth0_oidc-0.1.3.dist-info/WHEEL
panel_auth0_oidc-0.1.3.dist-info/METADATA
panel_auth0_oidc-0.1.3.dist-info/RECORD
