Metadata-Version: 2.1
Name: panel-auth0-oidc
Version: 0.1.3
Summary: Top-level package for Panel Auth0 Oidc.
Home-page: https://github.com/jmosbacher/panel_auth0_oidc
License: MIT
Author: Yossi Mosbacher
Author-email: joe.mosbacher@gmail.com
Requires-Python: >=3.7
Classifier: Development Status :: 2 - Pre-Alpha
Classifier: Intended Audience :: Developers
Classifier: License :: OSI Approved :: MIT License
Classifier: Natural Language :: English
Classifier: Programming Language :: Python :: 3
Classifier: Programming Language :: Python :: 3.7
Classifier: Programming Language :: Python :: 3.8
Requires-Dist: panel
